strands_deep_agents/__init__.py
strands_deep_agents/ai_models.py
strands_deep_agents/factory.py
strands_deep_agents/prompts.py
strands_deep_agents/state.py
strands_deep_agents/sub_agents.py
strands_deep_agents/types.py
strands_deep_agents/tools/__init__.py
strands_deep_agents/tools/planning.py
strands_deep_agents-0.1.1.dist-info/METADATA
strands_deep_agents-0.1.1.dist-info/WHEEL
strands_deep_agents-0.1.1.dist-info/licenses/LICENSE
strands_deep_agents-0.1.1.dist-info/RECORD
