Metadata-Version: 2.4
Name: strands-deep-agents
Version: 0.1.1
Summary: DeepAgents implementation using Strands Agents SDK - creating planning-capable agents with sub-agents and virtual file systems
Project-URL: Homepage, https://github.com/lemopian/strands-deep-agents/tree/main
Project-URL: Documentation, https://github.com/lemopian/strands-deep-agents/tree/main#readme
Project-URL: Repository, https://github.com/lemopian/strands-deep-agents/tree/main
Project-URL: Issues, https://github.com/lemopian/strands-deep-agents/tree/main/issues
Author: Strands DeepAgents Team
License: MIT
License-File: LICENSE
Keywords: agents,ai,deepagents,multi-agent,planning,strands
Classifier: Development Status :: 3 - Alpha
Classifier: Intended Audience :: Developers
Classifier: License :: OSI Approved :: MIT License
Classifier: Programming Language :: Python :: 3
Classifier: Programming Language :: Python :: 3.9
Classifier: Programming Language :: Python :: 3.10
Classifier: Programming Language :: Python :: 3.11
Classifier: Programming Language :: Python :: 3.12
Requires-Python: >=3.12
Requires-Dist: boto3>=1.40.50
Requires-Dist: dotenv>=0.9.9
Requires-Dist: strands-agents-tools>=0.1.0
Requires-Dist: strands-agents>=0.1.0
Provides-Extra: dev
Requires-Dist: black>=23.0.0; extra == 'dev'
Requires-Dist: mypy>=1.0.0; extra == 'dev'
Requires-Dist: pytest-asyncio>=0.21.0; extra == 'dev'
Requires-Dist: pytest>=7.0.0; extra == 'dev'
Requires-Dist: ruff>=0.1.0; extra == 'dev'
